rmonkey/__init__.py
rmonkey/action/__init__.py
rmonkey/action/tool_action.py
rmonkey/agents/__init__.py
rmonkey/agents/_base.py
rmonkey/agents/ask_agent.py
rmonkey/agents/root_monkey.py
rmonkey/agents/swe_agent.py
rmonkey/entrypoints/cli/main.py
rmonkey/llm/__init__.py
rmonkey/llm/providers/openai.py
rmonkey/memory/__init__.py
rmonkey/memory/memory.py
rmonkey/plan/__init__.py
rmonkey/plan/planning.py
rmonkey/tools/__init__.py
rmonkey/tools/_base.py
rmonkey/tools/code_interpreter.py
rmonkey/tools/human.py
rmonkey/tools/terminal_bash.py
rmonkey/tools/text_file_editor.py
rmonkey/tools/think.py
rmonkey/tools/tool_set.py
rmonkey/utils/__init__.py
rmonkey/utils/os_info.py
rmonkey/utils/pretty_console.py
rmonkey/utils/schema.py
rmonkey/utils/user_rules.py
rmonkey/utils/util.py
rmk-0.1.1.dist-info/METADATA
rmk-0.1.1.dist-info/WHEEL
rmk-0.1.1.dist-info/entry_points.txt
rmk-0.1.1.dist-info/RECORD
