Metadata-Version: 2.4
Name: rmk
Version: 0.1.1
Summary: Root Monkey (rmk) is an autonomous AI Agent system.
Project-URL: Homepage, https://github.com/rootagent
Project-URL: Repository, https://github.com/rootagent/rmk
Author-email: rootmq <mqvvang@gmail.com>
Requires-Python: >=3.10
Requires-Dist: anthropic>=0.52.0
Requires-Dist: dotenv>=0.9.9
Requires-Dist: litellm>=1.72.0
Requires-Dist: openai>=1.82.0
Requires-Dist: pydantic>=2.11.5
Requires-Dist: rich>=14.0.0
